{
  "flags": {},
  "shapes": [
    {
      "label": "Post-It",
      "line_color": null,
      "fill_color": null,
      "points": [
        [
          514,
          534
        ],
        [
          818,
          515
        ],
        [
          861,
          1004
        ],
        [
          561,
          1019
        ]
      ]
    },
    {
      "label": "Post-It",
      "line_color": null,
      "fill_color": null,
      "points": [
        [
          896,
          757
        ],
        [
          855,
          1030
        ],
        [
          1101,
          1066
        ],
        [
          1144,
          779
        ]
      ]
    },
    {
      "label": "Post-It",
      "line_color": null,
      "fill_color": null,
      "points": [
        [
          853,
          1064
        ],
        [
          1073,
          1047
        ],
        [
          1103,
          1334
        ],
        [
          872,
          1351
        ]
      ]
    },
    {
      "label": "Post-It",
      "line_color": null,
      "fill_color": null,
      "points": [
        [
          1256,
          687
        ],
        [
          1532,
          669
        ],
        [
          1566,
          957
        ],
        [
          1286,
          967
        ]
      ]
    },
    {
      "label": "Post-It",
      "line_color": null,
      "fill_color": null,
      "points": [
        [
          1116,
          1087
        ],
        [
          1352,
          1053
        ],
        [
          1376,
          1338
        ],
        [
          1151,
          1364
        ]
      ]
    },
    {
      "label": "Post-It",
      "line_color": null,
      "fill_color": null,
      "points": [
        [
          1623,
          570
        ],
        [
          1890,
          604
        ],
        [
          1866,
          872
        ],
        [
          1598,
          837
        ]
      ]
    },
    {
      "label": "Post-It",
      "line_color": null,
      "fill_color": null,
      "points": [
        [
          1616,
          869
        ],
        [
          1886,
          881
        ],
        [
          1887,
          1148
        ],
        [
          1624,
          1137
        ]
      ]
    },
    {
      "label": "Post-It",
      "line_color": null,
      "fill_color": null,
      "points": [
        [
          2042,
          836
        ],
        [
          2285,
          916
        ],
        [
          2214,
          1161
        ],
        [
          1969,
          1082
        ]
      ]
    },
    {
      "label": "Post-It",
      "line_color": null,
      "fill_color": null,
      "points": [
        [
          2373,
          930
        ],
        [
          2619,
          932
        ],
        [
          2623,
          1183
        ],
        [
          2380,
          1188
        ]
      ]
    },
    {
      "label": "Post-It",
      "line_color": null,
      "fill_color": null,
      "points": [
        [
          1443,
          1791
        ],
        [
          1713,
          1790
        ],
        [
          1718,
          2059
        ],
        [
          1447,
          2061
        ]
      ]
    },
    {
      "label": "Post-It",
      "line_color": null,
      "fill_color": null,
      "points": [
        [
          2007,
          159
        ],
        [
          2268,
          209
        ],
        [
          2240,
          476
        ],
        [
          1983,
          436
        ]
      ]
    },
    {
      "label": "Post-It",
      "line_color": null,
      "fill_color": null,
      "points": [
        [
          2692,
          311
        ],
        [
          2931,
          330
        ],
        [
          2921,
          582
        ],
        [
          2687,
          565
        ]
      ]
    },
    {
      "label": "Post-It",
      "line_color": null,
      "fill_color": null,
      "points": [
        [
          3229,
          432
        ],
        [
          3455,
          479
        ],
        [
          3422,
          722
        ],
        [
          3194,
          681
        ]
      ]
    },
    {
      "label": "Post-It",
      "line_color": null,
      "fill_color": null,
      "points": [
        [
          3285,
          101
        ],
        [
          3503,
          148
        ],
        [
          3471,
          393
        ],
        [
          3251,
          340
        ]
      ]
    },
    {
      "label": "Post-It",
      "line_color": null,
      "fill_color": null,
      "points": [
        [
          3539,
          128
        ],
        [
          3746,
          161
        ],
        [
          3745,
          385
        ],
        [
          3533,
          358
        ]
      ]
    },
    {
      "label": "Post-It",
      "line_color": null,
      "fill_color": null,
      "points": [
        [
          3538,
          394
        ],
        [
          3750,
          420
        ],
        [
          3743,
          647
        ],
        [
          3534,
          630
        ]
      ]
    },
    {
      "label": "Post-It",
      "line_color": null,
      "fill_color": null,
      "points": [
        [
          3485,
          795
        ],
        [
          3253,
          821
        ],
        [
          3289,
          1216
        ],
        [
          3512,
          1196
        ]
      ]
    },
    {
      "label": "Post-It",
      "line_color": null,
      "fill_color": null,
      "points": [
        [
          3650,
          900
        ],
        [
          3875,
          923
        ],
        [
          3863,
          1160
        ],
        [
          3634,
          1139
        ]
      ]
    },
    {
      "label": "Post-It",
      "line_color": null,
      "fill_color": null,
      "points": [
        [
          3594,
          1210
        ],
        [
          3807,
          1206
        ],
        [
          3807,
          1444
        ],
        [
          3597,
          1435
        ]
      ]
    },
    {
      "label": "Post-It",
      "line_color": null,
      "fill_color": null,
      "points": [
        [
          3826,
          1198
        ],
        [
          4027,
          1161
        ],
        [
          4068,
          1390
        ],
        [
          3862,
          1428
        ]
      ]
    },
    {
      "label": "Post-It",
      "line_color": null,
      "fill_color": null,
      "points": [
        [
          3443,
          1380
        ],
        [
          3693,
          1340
        ],
        [
          3735,
          1579
        ],
        [
          3486,
          1611
        ]
      ]
    },
    {
      "label": "Post-It",
      "line_color": null,
      "fill_color": null,
      "points": [
        [
          3796,
          1432
        ],
        [
          4002,
          1428
        ],
        [
          4006,
          1658
        ],
        [
          3804,
          1667
        ]
      ]
    },
    {
      "label": "Post-It",
      "line_color": null,
      "fill_color": null,
      "points": [
        [
          3351,
          1677
        ],
        [
          3581,
          1701
        ],
        [
          3549,
          2093
        ],
        [
          3324,
          2072
        ]
      ]
    },
    {
      "label": "Post-It",
      "line_color": null,
      "fill_color": null,
      "points": [
        [
          3567,
          1682
        ],
        [
          3575,
          2068
        ],
        [
          3800,
          2066
        ],
        [
          3796,
          1672
        ]
      ]
    },
    {
      "label": "Post-It",
      "line_color": null,
      "fill_color": null,
      "points": [
        [
          3521,
          2101
        ],
        [
          3740,
          2101
        ],
        [
          3756,
          2489
        ],
        [
          3525,
          2499
        ]
      ]
    },
    {
      "label": "Post-It",
      "line_color": null,
      "fill_color": null,
      "points": [
        [
          3512,
          2547
        ],
        [
          3722,
          2501
        ],
        [
          3756,
          2730
        ],
        [
          3546,
          2778
        ]
      ]
    },
    {
      "label": "Post-It",
      "line_color": null,
      "fill_color": null,
      "points": [
        [
          2244,
          1498
        ],
        [
          2480,
          1512
        ],
        [
          2478,
          1759
        ],
        [
          2235,
          1753
        ]
      ]
    },
    {
      "label": "Post-It",
      "line_color": null,
      "fill_color": null,
      "points": [
        [
          2523,
          1519
        ],
        [
          2763,
          1555
        ],
        [
          2729,
          1798
        ],
        [
          2495,
          1765
        ]
      ]
    },
    {
      "label": "Post-It",
      "line_color": null,
      "fill_color": null,
      "points": [
        [
          2863,
          1552
        ],
        [
          3097,
          1567
        ],
        [
          3087,
          1808
        ],
        [
          2848,
          1791
        ]
      ]
    },
    {
      "label": "Post-It",
      "line_color": null,
      "fill_color": null,
      "points": [
        [
          2829,
          1871
        ],
        [
          3052,
          1883
        ],
        [
          3031,
          2124
        ],
        [
          2798,
          2111
        ]
      ]
    },
    {
      "label": "Post-It",
      "line_color": null,
      "fill_color": null,
      "points": [
        [
          2803,
          1838
        ],
        [
          2798,
          2077
        ],
        [
          2563,
          2084
        ],
        [
          2568,
          1840
        ]
      ]
    },
    {
      "label": "Post-It",
      "line_color": null,
      "fill_color": null,
      "points": [
        [
          2267,
          1826
        ],
        [
          2516,
          1834
        ],
        [
          2507,
          2082
        ],
        [
          2262,
          2079
        ]
      ]
    },
    {
      "label": "Post-It",
      "line_color": null,
      "fill_color": null,
      "points": [
        [
          2255,
          2163
        ],
        [
          2497,
          2140
        ],
        [
          2512,
          2378
        ],
        [
          2267,
          2410
        ]
      ]
    },
    {
      "label": "Post-It",
      "line_color": null,
      "fill_color": null,
      "points": [
        [
          2589,
          2100
        ],
        [
          2825,
          2133
        ],
        [
          2802,
          2366
        ],
        [
          2560,
          2346
        ]
      ]
    },
    {
      "label": "Post-It",
      "line_color": null,
      "fill_color": null,
      "points": [
        [
          2880,
          2179
        ],
        [
          3104,
          2158
        ],
        [
          3124,
          2394
        ],
        [
          2895,
          2425
        ]
      ]
    },
    {
      "label": "Post-It",
      "line_color": null,
      "fill_color": null,
      "points": [
        [
          1920,
          1779
        ],
        [
          2174,
          1762
        ],
        [
          2192,
          2016
        ],
        [
          1939,
          2038
        ]
      ]
    },
    {
      "label": "Post-It",
      "line_color": null,
      "fill_color": null,
      "points": [
        [
          1957,
          2047
        ],
        [
          2210,
          2035
        ],
        [
          2220,
          2291
        ],
        [
          1969,
          2307
        ]
      ]
    },
    {
      "label": "Post-It",
      "line_color": null,
      "fill_color": null,
      "points": [
        [
          961,
          2510
        ],
        [
          1187,
          2528
        ],
        [
          1198,
          2817
        ],
        [
          975,
          2790
        ]
      ]
    },
    {
      "label": "Post-It",
      "line_color": null,
      "fill_color": null,
      "points": [
        [
          975,
          2828
        ],
        [
          1217,
          2867
        ],
        [
          1203,
          3116
        ],
        [
          961,
          3101
        ]
      ]
    },
    {
      "label": "Post-It",
      "line_color": null,
      "fill_color": null,
      "points": [
        [
          1285,
          2462
        ],
        [
          1560,
          2480
        ],
        [
          1539,
          2753
        ],
        [
          1257,
          2742
        ]
      ]
    },
    {
      "label": "Post-It",
      "line_color": null,
      "fill_color": null,
      "points": [
        [
          1569,
          2487
        ],
        [
          1842,
          2491
        ],
        [
          1827,
          2766
        ],
        [
          1557,
          2758
        ]
      ]
    },
    {
      "label": "Post-It",
      "line_color": null,
      "fill_color": null,
      "points": [
        [
          2408,
          2718
        ],
        [
          2646,
          2711
        ],
        [
          2649,
          2958
        ],
        [
          2401,
          2970
        ]
      ]
    },
    {
      "label": "Text",
      "line_color": null,
      "fill_color": null,
      "points": [
        [
          450,
          3077
        ],
        [
          450,
          1377
        ],
        [
          107,
          1392
        ],
        [
          128,
          3111
        ]
      ]
    },
    {
      "label": "Text",
      "line_color": null,
      "fill_color": null,
      "points": [
        [
          565,
          997
        ],
        [
          818,
          997
        ],
        [
          769,
          1947
        ],
        [
          533,
          1968
        ]
      ]
    },
    {
      "label": "Text",
      "line_color": null,
      "fill_color": null,
      "points": [
        [
          402,
          1184
        ],
        [
          396,
          1
        ],
        [
          113,
          5
        ],
        [
          105,
          1175
        ]
      ]
    },
    {
      "label": "Text",
      "line_color": null,
      "fill_color": null,
      "points": [
        [
          1002,
          2424
        ],
        [
          1005,
          1997
        ],
        [
          823,
          1991
        ],
        [
          816,
          2438
        ]
      ]
    },
    {
      "label": "Text",
      "line_color": null,
      "fill_color": null,
      "points": [
        [
          872,
          1930
        ],
        [
          869,
          1823
        ],
        [
          991,
          1834
        ],
        [
          988,
          1944
        ]
      ]
    },
    {
      "label": "Text",
      "line_color": null,
      "fill_color": null,
      "points": [
        [
          900,
          1652
        ],
        [
          892,
          1758
        ],
        [
          991,
          1766
        ],
        [
          994,
          1653
        ]
      ]
    },
    {
      "label": "Text",
      "line_color": null,
      "fill_color": null,
      "points": [
        [
          1211,
          2311
        ],
        [
          1217,
          2062
        ],
        [
          1147,
          2070
        ],
        [
          1120,
          2325
        ]
      ]
    },
    {
      "label": "Text",
      "line_color": null,
      "fill_color": null,
      "points": [
        [
          1226,
          2006
        ],
        [
          1218,
          1911
        ],
        [
          1130,
          1910
        ],
        [
          1133,
          2006
        ]
      ]
    },
    {
      "label": "Text",
      "line_color": null,
      "fill_color": null,
      "points": [
        [
          1221,
          1839
        ],
        [
          1240,
          1628
        ],
        [
          1180,
          1630
        ],
        [
          1154,
          1845
        ]
      ]
    },
    {
      "label": "Text",
      "line_color": null,
      "fill_color": null,
      "points": [
        [
          1315,
          1841
        ],
        [
          1318,
          1726
        ],
        [
          1247,
          1736
        ],
        [
          1279,
          1852
        ]
      ]
    },
    {
      "label": "Text",
      "line_color": null,
      "fill_color": null,
      "points": [
        [
          1300,
          2302
        ],
        [
          1313,
          1893
        ],
        [
          1253,
          1893
        ],
        [
          1241,
          2300
        ]
      ]
    },
    {
      "label": "Text",
      "line_color": null,
      "fill_color": null,
      "points": [
        [
          1387,
          2287
        ],
        [
          1402,
          2050
        ],
        [
          1339,
          2052
        ],
        [
          1319,
          2298
        ]
      ]
    },
    {
      "label": "Text",
      "line_color": null,
      "fill_color": null,
      "points": [
        [
          1404,
          1994
        ],
        [
          1451,
          1610
        ],
        [
          1351,
          1616
        ],
        [
          1332,
          1999
        ]
      ]
    },
    {
      "label": "Text",
      "line_color": null,
      "fill_color": null,
      "points": [
        [
          1714,
          2913
        ],
        [
          1716,
          3032
        ],
        [
          1736,
          3028
        ],
        [
          1741,
          2912
        ]
      ]
    },
    {
      "label": "Text",
      "line_color": null,
      "fill_color": null,
      "points": [
        [
          1418,
          19
        ],
        [
          1413,
          197
        ],
        [
          1328,
          201
        ],
        [
          1336,
          3
        ]
      ]
    }
  ],
  "labels": [],
  "lineColor": [
    0,
    255,
    0,
    128
  ],
  "fillColor": [
    255,
    0,
    0,
    128
  ],
  "imagePath": "IMG_20190129_171321.jpg",
  "imageData": null
}